[
  {
    "Player": "Shane Bieber",
    "Season": 2020,
    "ERA": 1.63,
    "WHIP": 0.866,
    "Kpct": 41.0774,
    "BBpct": 7.0707,
    "KBB": 5.81,
    "IP": 77.1,
    "HR9": 0.8,
    "FIP": 2.07,
    "W": 8,
    "L": 1
  },
  {
    "Player": "Jacob deGrom",
    "Season": 2020,
    "ERA": 2.38,
    "WHIP": 0.956,
    "Kpct": 35.0168,
    "BBpct": 6.0606,
    "KBB": 5.78,
    "IP": 68,
    "HR9": 0.9,
    "FIP": 2.26,
    "W": 4,
    "L": 2
  },
  {
    "Player": "Trevor Bauer",
    "Season": 2020,
    "ERA": 1.73,
    "WHIP": 0.795,
    "Kpct": 33.67,
    "BBpct": 5.7239,
    "KBB": 5.88,
    "IP": 73,
    "HR9": 1.1,
    "FIP": 2.88,
    "W": 5,
    "L": 4
  },
  {
    "Player": "Lucas Giolito",
    "Season": 2020,
    "ERA": 3.48,
    "WHIP": 1.037,
    "Kpct": 32.6599,
    "BBpct": 9.4276,
    "KBB": 3.46,
    "IP": 72.1,
    "HR9": 1,
    "FIP": 3.19,
    "W": 4,
    "L": 3
  },
  {
    "Player": "Aaron Nola",
    "Season": 2020,
    "ERA": 3.28,
    "WHIP": 1.079,
    "Kpct": 32.3232,
    "BBpct": 7.7441,
    "KBB": 4.17,
    "IP": 71.1,
    "HR9": 1.1,
    "FIP": 3.19,
    "W": 5,
    "L": 5
  },
  {
    "Player": "Gerrit Cole",
    "Season": 2020,
    "ERA": 2.84,
    "WHIP": 0.959,
    "Kpct": 31.6498,
    "BBpct": 5.7239,
    "KBB": 5.53,
    "IP": 73,
    "HR9": 1.7,
    "FIP": 3.89,
    "W": 7,
    "L": 3
  },
  {
    "Player": "Yu Darvish",
    "Season": 2020,
    "ERA": 2.01,
    "WHIP": 0.961,
    "Kpct": 31.3131,
    "BBpct": 4.7138,
    "KBB": 6.64,
    "IP": 76,
    "HR9": 0.6,
    "FIP": 2.23,
    "W": 8,
    "L": 3
  },
  {
    "Player": "Dinelson Lamet",
    "Season": 2020,
    "ERA": 2.09,
    "WHIP": 0.855,
    "Kpct": 31.3131,
    "BBpct": 6.734,
    "KBB": 4.65,
    "IP": 69,
    "HR9": 0.7,
    "FIP": 2.48,
    "W": 3,
    "L": 1
  },
  {
    "Player": "Max Scherzer",
    "Season": 2020,
    "ERA": 3.74,
    "WHIP": 1.381,
    "Kpct": 30.9764,
    "BBpct": 7.7441,
    "KBB": 4,
    "IP": 67.1,
    "HR9": 1.3,
    "FIP": 3.46,
    "W": 5,
    "L": 4
  },
  {
    "Player": "Tyler Glasnow",
    "Season": 2020,
    "ERA": 4.08,
    "WHIP": 1.134,
    "Kpct": 30.6397,
    "BBpct": 7.4074,
    "KBB": 4.14,
    "IP": 57.1,
    "HR9": 1.7,
    "FIP": 3.66,
    "W": 5,
    "L": 1
  },
  {
    "Player": "Brandon Woodruff",
    "Season": 2020,
    "ERA": 3.05,
    "WHIP": 0.991,
    "Kpct": 30.6397,
    "BBpct": 6.0606,
    "KBB": 5.06,
    "IP": 73.2,
    "HR9": 1.1,
    "FIP": 3.2,
    "W": 3,
    "L": 5
  },
  {
    "Player": "Luis Castillo",
    "Season": 2020,
    "ERA": 3.21,
    "WHIP": 1.229,
    "Kpct": 29.9663,
    "BBpct": 8.0808,
    "KBB": 3.71,
    "IP": 70,
    "HR9": 0.6,
    "FIP": 2.65,
    "W": 4,
    "L": 6
  },
  {
    "Player": "Lance Lynn",
    "Season": 2020,
    "ERA": 3.32,
    "WHIP": 1.06,
    "Kpct": 29.9663,
    "BBpct": 8.4175,
    "KBB": 3.56,
    "IP": 84,
    "HR9": 1.4,
    "FIP": 4.19,
    "W": 6,
    "L": 3
  },
  {
    "Player": "Corbin Burnes",
    "Season": 2020,
    "ERA": 2.11,
    "WHIP": 1.022,
    "Kpct": 29.6296,
    "BBpct": 8.0808,
    "KBB": 3.67,
    "IP": 59.2,
    "HR9": 0.3,
    "FIP": 2.03,
    "W": 4,
    "L": 1
  },
  {
    "Player": "Carlos Carrasco",
    "Season": 2020,
    "ERA": 2.91,
    "WHIP": 1.206,
    "Kpct": 27.6094,
    "BBpct": 9.0909,
    "KBB": 3.04,
    "IP": 68,
    "HR9": 1.1,
    "FIP": 3.59,
    "W": 3,
    "L": 4
  },
  {
    "Player": "Zac Gallen",
    "Season": 2020,
    "ERA": 2.75,
    "WHIP": 1.111,
    "Kpct": 27.6094,
    "BBpct": 8.4175,
    "KBB": 3.28,
    "IP": 72,
    "HR9": 1.1,
    "FIP": 3.66,
    "W": 3,
    "L": 2
  },
  {
    "Player": "Kenta Maeda",
    "Season": 2020,
    "ERA": 2.7,
    "WHIP": 0.75,
    "Kpct": 26.936,
    "BBpct": 3.367,
    "KBB": 8,
    "IP": 66.2,
    "HR9": 1.2,
    "FIP": 3,
    "W": 6,
    "L": 1
  },
  {
    "Player": "Kevin Gausman",
    "Season": 2020,
    "ERA": 3.62,
    "WHIP": 1.106,
    "Kpct": 26.5993,
    "BBpct": 5.3872,
    "KBB": 4.94,
    "IP": 59.2,
    "HR9": 1.2,
    "FIP": 3.09,
    "W": 3,
    "L": 3
  },
  {
    "Player": "Framber Valdez",
    "Season": 2020,
    "ERA": 3.57,
    "WHIP": 1.118,
    "Kpct": 25.5892,
    "BBpct": 5.3872,
    "KBB": 4.75,
    "IP": 70.2,
    "HR9": 0.6,
    "FIP": 2.85,
    "W": 5,
    "L": 3
  },
  {
    "Player": "Germán Márquez",
    "Season": 2020,
    "ERA": 3.75,
    "WHIP": 1.261,
    "Kpct": 24.5791,
    "BBpct": 8.4175,
    "KBB": 2.92,
    "IP": 81.2,
    "HR9": 0.7,
    "FIP": 3.28,
    "W": 4,
    "L": 6
  },
  {
    "Player": "Dylan Bundy",
    "Season": 2020,
    "ERA": 3.29,
    "WHIP": 1.036,
    "Kpct": 24.2424,
    "BBpct": 5.7239,
    "KBB": 4.24,
    "IP": 65.2,
    "HR9": 0.7,
    "FIP": 2.95,
    "W": 6,
    "L": 3
  },
  {
    "Player": "Sonny Gray",
    "Season": 2020,
    "ERA": 3.7,
    "WHIP": 1.214,
    "Kpct": 24.2424,
    "BBpct": 8.7542,
    "KBB": 2.77,
    "IP": 56,
    "HR9": 0.6,
    "FIP": 3.05,
    "W": 5,
    "L": 3
  },
  {
    "Player": "Hyun Jin Ryu",
    "Season": 2020,
    "ERA": 2.69,
    "WHIP": 1.149,
    "Kpct": 24.2424,
    "BBpct": 5.7239,
    "KBB": 4.24,
    "IP": 67,
    "HR9": 0.8,
    "FIP": 3.01,
    "W": 5,
    "L": 2
  },
  {
    "Player": "Zach Eflin",
    "Season": 2020,
    "ERA": 3.97,
    "WHIP": 1.271,
    "Kpct": 23.569,
    "BBpct": 5.0505,
    "KBB": 4.67,
    "IP": 59,
    "HR9": 1.2,
    "FIP": 3.39,
    "W": 4,
    "L": 2
  },
  {
    "Player": "Andrew Heaney",
    "Season": 2020,
    "ERA": 4.46,
    "WHIP": 1.23,
    "Kpct": 23.569,
    "BBpct": 6.3973,
    "KBB": 3.68,
    "IP": 66.2,
    "HR9": 1.2,
    "FIP": 3.79,
    "W": 4,
    "L": 3
  },
  {
    "Player": "Aaron Civale",
    "Season": 2020,
    "ERA": 4.74,
    "WHIP": 1.324,
    "Kpct": 23.2323,
    "BBpct": 5.3872,
    "KBB": 4.31,
    "IP": 74,
    "HR9": 1.3,
    "FIP": 4.03,
    "W": 4,
    "L": 6
  },
  {
    "Player": "José Berríos",
    "Season": 2020,
    "ERA": 4,
    "WHIP": 1.317,
    "Kpct": 22.8956,
    "BBpct": 8.7542,
    "KBB": 2.62,
    "IP": 63,
    "HR9": 1.1,
    "FIP": 4.06,
    "W": 5,
    "L": 4
  },
  {
    "Player": "Robbie Ray",
    "Season": 2020,
    "ERA": 6.62,
    "WHIP": 1.897,
    "Kpct": 22.8956,
    "BBpct": 15.1515,
    "KBB": 1.51,
    "IP": 51.2,
    "HR9": 2.3,
    "FIP": 6.5,
    "W": 2,
    "L": 5
  },
  {
    "Player": "Zack Greinke",
    "Season": 2020,
    "ERA": 4.03,
    "WHIP": 1.134,
    "Kpct": 22.5589,
    "BBpct": 3.0303,
    "KBB": 7.44,
    "IP": 67,
    "HR9": 0.8,
    "FIP": 2.8,
    "W": 3,
    "L": 3
  },
  {
    "Player": "Marco Gonzales",
    "Season": 2020,
    "ERA": 3.1,
    "WHIP": 0.947,
    "Kpct": 21.5488,
    "BBpct": 2.3569,
    "KBB": 9.14,
    "IP": 69.2,
    "HR9": 1,
    "FIP": 3.32,
    "W": 7,
    "L": 2
  },
  {
    "Player": "Kyle Hendricks",
    "Season": 2020,
    "ERA": 2.88,
    "WHIP": 0.996,
    "Kpct": 21.5488,
    "BBpct": 2.6936,
    "KBB": 8,
    "IP": 81.1,
    "HR9": 1.1,
    "FIP": 3.55,
    "W": 6,
    "L": 5
  },
  {
    "Player": "Zach Davies",
    "Season": 2020,
    "ERA": 2.73,
    "WHIP": 1.067,
    "Kpct": 21.2121,
    "BBpct": 6.3973,
    "KBB": 3.32,
    "IP": 69.1,
    "HR9": 1.2,
    "FIP": 3.88,
    "W": 7,
    "L": 4
  },
  {
    "Player": "Blake Snell",
    "Season": 2020,
    "ERA": 3.24,
    "WHIP": 1.2,
    "Kpct": 21.2121,
    "BBpct": 6.0606,
    "KBB": 3.5,
    "IP": 50,
    "HR9": 1.8,
    "FIP": 4.35,
    "W": 4,
    "L": 2
  },
  {
    "Player": "Clayton Kershaw",
    "Season": 2020,
    "ERA": 2.16,
    "WHIP": 0.84,
    "Kpct": 20.8754,
    "BBpct": 2.6936,
    "KBB": 7.75,
    "IP": 58.1,
    "HR9": 1.2,
    "FIP": 3.31,
    "W": 6,
    "L": 2
  },
  {
    "Player": "Mike Minor",
    "Season": 2020,
    "ERA": 5.56,
    "WHIP": 1.235,
    "Kpct": 20.8754,
    "BBpct": 6.734,
    "KBB": 3.1,
    "IP": 56.2,
    "HR9": 1.7,
    "FIP": 4.64,
    "W": 1,
    "L": 6
  },
  {
    "Player": "Brady Singer",
    "Season": 2020,
    "ERA": 4.06,
    "WHIP": 1.166,
    "Kpct": 20.5387,
    "BBpct": 7.7441,
    "KBB": 2.65,
    "IP": 64.1,
    "HR9": 1.1,
    "FIP": 4.08,
    "W": 4,
    "L": 5
  },
  {
    "Player": "Matthew Boyd",
    "Season": 2020,
    "ERA": 6.71,
    "WHIP": 1.475,
    "Kpct": 20.202,
    "BBpct": 7.4074,
    "KBB": 2.73,
    "IP": 60.1,
    "HR9": 2.2,
    "FIP": 5.78,
    "W": 3,
    "L": 7
  },
  {
    "Player": "Patrick Corbin",
    "Season": 2020,
    "ERA": 4.66,
    "WHIP": 1.569,
    "Kpct": 20.202,
    "BBpct": 6.0606,
    "KBB": 3.33,
    "IP": 65.2,
    "HR9": 1.4,
    "FIP": 4.17,
    "W": 2,
    "L": 7
  },
  {
    "Player": "Tyler Mahle",
    "Season": 2020,
    "ERA": 3.59,
    "WHIP": 1.154,
    "Kpct": 20.202,
    "BBpct": 7.0707,
    "KBB": 2.86,
    "IP": 47.2,
    "HR9": 1.1,
    "FIP": 3.88,
    "W": 2,
    "L": 2
  },
  {
    "Player": "Frankie Montas",
    "Season": 2020,
    "ERA": 5.6,
    "WHIP": 1.509,
    "Kpct": 20.202,
    "BBpct": 7.7441,
    "KBB": 2.61,
    "IP": 53,
    "HR9": 1.7,
    "FIP": 4.74,
    "W": 3,
    "L": 5
  },
  {
    "Player": "Pablo López",
    "Season": 2020,
    "ERA": 3.61,
    "WHIP": 1.186,
    "Kpct": 19.8653,
    "BBpct": 6.0606,
    "KBB": 3.28,
    "IP": 57.1,
    "HR9": 0.6,
    "FIP": 3.09,
    "W": 6,
    "L": 4
  },
  {
    "Player": "Jesús Luzardo",
    "Season": 2020,
    "ERA": 4.12,
    "WHIP": 1.271,
    "Kpct": 19.8653,
    "BBpct": 5.7239,
    "KBB": 3.47,
    "IP": 59,
    "HR9": 1.4,
    "FIP": 4.19,
    "W": 3,
    "L": 2
  },
  {
    "Player": "Kyle Gibson",
    "Season": 2020,
    "ERA": 5.35,
    "WHIP": 1.53,
    "Kpct": 19.5286,
    "BBpct": 10.101,
    "KBB": 1.93,
    "IP": 67.1,
    "HR9": 1.6,
    "FIP": 5.39,
    "W": 2,
    "L": 6
  },
  {
    "Player": "Chris Paddack",
    "Season": 2020,
    "ERA": 4.73,
    "WHIP": 1.22,
    "Kpct": 19.5286,
    "BBpct": 4.0404,
    "KBB": 4.83,
    "IP": 59,
    "HR9": 2.1,
    "FIP": 5.02,
    "W": 4,
    "L": 5
  },
  {
    "Player": "Danny Duffy",
    "Season": 2020,
    "ERA": 4.95,
    "WHIP": 1.331,
    "Kpct": 19.1919,
    "BBpct": 7.4074,
    "KBB": 2.59,
    "IP": 56.1,
    "HR9": 1.6,
    "FIP": 4.75,
    "W": 4,
    "L": 4
  },
  {
    "Player": "Zach Plesac",
    "Season": 2020,
    "ERA": 2.28,
    "WHIP": 0.795,
    "Kpct": 19.1919,
    "BBpct": 2.0202,
    "KBB": 9.5,
    "IP": 55.1,
    "HR9": 1.3,
    "FIP": 3.39,
    "W": 4,
    "L": 2
  },
  {
    "Player": "Griffin Canning",
    "Season": 2020,
    "ERA": 3.99,
    "WHIP": 1.367,
    "Kpct": 18.8552,
    "BBpct": 7.7441,
    "KBB": 2.43,
    "IP": 56.1,
    "HR9": 1.3,
    "FIP": 4.33,
    "W": 2,
    "L": 3
  },
  {
    "Player": "Johnny Cueto",
    "Season": 2020,
    "ERA": 5.4,
    "WHIP": 1.374,
    "Kpct": 18.8552,
    "BBpct": 8.7542,
    "KBB": 2.15,
    "IP": 63.1,
    "HR9": 1.3,
    "FIP": 4.64,
    "W": 2,
    "L": 3
  },
  {
    "Player": "Lance McCullers Jr.",
    "Season": 2020,
    "ERA": 3.93,
    "WHIP": 1.164,
    "Kpct": 18.8552,
    "BBpct": 6.734,
    "KBB": 2.8,
    "IP": 55,
    "HR9": 0.8,
    "FIP": 3.7,
    "W": 3,
    "L": 3
  },
  {
    "Player": "Chris Bassitt",
    "Season": 2020,
    "ERA": 2.29,
    "WHIP": 1.159,
    "Kpct": 18.5185,
    "BBpct": 5.7239,
    "KBB": 3.24,
    "IP": 63,
    "HR9": 0.9,
    "FIP": 3.59,
    "W": 5,
    "L": 2
  },
  {
    "Player": "Joe Musgrove",
    "Season": 2020,
    "ERA": 3.86,
    "WHIP": 1.235,
    "Kpct": 18.5185,
    "BBpct": 5.3872,
    "KBB": 3.44,
    "IP": 39.2,
    "HR9": 1.1,
    "FIP": 3.42,
    "W": 1,
    "L": 5
  },
  {
    "Player": "Luke Weaver",
    "Season": 2020,
    "ERA": 6.58,
    "WHIP": 1.558,
    "Kpct": 18.5185,
    "BBpct": 6.0606,
    "KBB": 3.06,
    "IP": 52,
    "HR9": 1.7,
    "FIP": 4.67,
    "W": 1,
    "L": 9
  },
  {
    "Player": "Cristian Javier",
    "Season": 2020,
    "ERA": 3.48,
    "WHIP": 0.994,
    "Kpct": 18.1818,
    "BBpct": 6.0606,
    "KBB": 3,
    "IP": 54.1,
    "HR9": 1.8,
    "FIP": 4.94,
    "W": 5,
    "L": 2
  },
  {
    "Player": "Rick Porcello",
    "Season": 2020,
    "ERA": 5.64,
    "WHIP": 1.508,
    "Kpct": 18.1818,
    "BBpct": 5.0505,
    "KBB": 3.6,
    "IP": 59,
    "HR9": 0.8,
    "FIP": 3.33,
    "W": 1,
    "L": 7
  },
  {
    "Player": "Adam Wainwright",
    "Season": 2020,
    "ERA": 3.15,
    "WHIP": 1.051,
    "Kpct": 18.1818,
    "BBpct": 5.0505,
    "KBB": 3.6,
    "IP": 65.2,
    "HR9": 1.2,
    "FIP": 4.1,
    "W": 5,
    "L": 3
  },
  {
    "Player": "James Karinchak",
    "Season": 2020,
    "ERA": 2.67,
    "WHIP": 1.111,
    "Kpct": 17.8451,
    "BBpct": 5.3872,
    "KBB": 3.31,
    "IP": 27,
    "HR9": 0.3,
    "FIP": 1.52,
    "W": 1,
    "L": 2
  },
  {
    "Player": "Zack Wheeler",
    "Season": 2020,
    "ERA": 2.92,
    "WHIP": 1.169,
    "Kpct": 17.8451,
    "BBpct": 5.3872,
    "KBB": 3.31,
    "IP": 71,
    "HR9": 0.4,
    "FIP": 3.22,
    "W": 4,
    "L": 2
  },
  {
    "Player": "Devin Williams",
    "Season": 2020,
    "ERA": 0.33,
    "WHIP": 0.63,
    "Kpct": 17.8451,
    "BBpct": 3.0303,
    "KBB": 5.89,
    "IP": 27,
    "HR9": 0.3,
    "FIP": 0.86,
    "W": 4,
    "L": 1
  },
  {
    "Player": "Nathan Eovaldi",
    "Season": 2020,
    "ERA": 3.72,
    "WHIP": 1.2,
    "Kpct": 17.5084,
    "BBpct": 2.3569,
    "KBB": 7.43,
    "IP": 48.1,
    "HR9": 1.5,
    "FIP": 3.87,
    "W": 4,
    "L": 2
  },
  {
    "Player": "Josh Lindblom",
    "Season": 2020,
    "ERA": 5.16,
    "WHIP": 1.279,
    "Kpct": 17.5084,
    "BBpct": 5.3872,
    "KBB": 3.25,
    "IP": 45.1,
    "HR9": 1.2,
    "FIP": 3.87,
    "W": 2,
    "L": 4
  },
  {
    "Player": "Spencer Turnbull",
    "Season": 2020,
    "ERA": 3.97,
    "WHIP": 1.341,
    "Kpct": 17.1717,
    "BBpct": 9.7643,
    "KBB": 1.76,
    "IP": 56.2,
    "HR9": 0.3,
    "FIP": 3.49,
    "W": 4,
    "L": 4
  },
  {
    "Player": "Edwin Díaz",
    "Season": 2020,
    "ERA": 1.75,
    "WHIP": 1.247,
    "Kpct": 16.835,
    "BBpct": 4.7138,
    "KBB": 3.57,
    "IP": 25.2,
    "HR9": 0.7,
    "FIP": 2.18,
    "W": 2,
    "L": 1
  },
  {
    "Player": "Max Fried",
    "Season": 2020,
    "ERA": 2.25,
    "WHIP": 1.089,
    "Kpct": 16.835,
    "BBpct": 6.3973,
    "KBB": 2.63,
    "IP": 56,
    "HR9": 0.3,
    "FIP": 3.1,
    "W": 7,
    "L": 0
  },
  {
    "Player": "Taijuan Walker",
    "Season": 2020,
    "ERA": 2.7,
    "WHIP": 1.163,
    "Kpct": 16.835,
    "BBpct": 6.3973,
    "KBB": 2.63,
    "IP": 53.1,
    "HR9": 1.4,
    "FIP": 4.56,
    "W": 4,
    "L": 3
  },
  {
    "Player": "Kris Bubic",
    "Season": 2020,
    "ERA": 4.32,
    "WHIP": 1.48,
    "Kpct": 16.4983,
    "BBpct": 7.4074,
    "KBB": 2.23,
    "IP": 50,
    "HR9": 1.4,
    "FIP": 4.75,
    "W": 1,
    "L": 6
  },
  {
    "Player": "Jack Flaherty",
    "Season": 2020,
    "ERA": 4.91,
    "WHIP": 1.215,
    "Kpct": 16.4983,
    "BBpct": 5.3872,
    "KBB": 3.06,
    "IP": 40.1,
    "HR9": 1.3,
    "FIP": 4.11,
    "W": 4,
    "L": 3
  },
  {
    "Player": "Trevor Williams",
    "Season": 2020,
    "ERA": 6.18,
    "WHIP": 1.572,
    "Kpct": 16.4983,
    "BBpct": 7.0707,
    "KBB": 2.33,
    "IP": 55.1,
    "HR9": 2.4,
    "FIP": 6.3,
    "W": 2,
    "L": 8
  },
  {
    "Player": "JT Brubaker",
    "Season": 2020,
    "ERA": 4.94,
    "WHIP": 1.373,
    "Kpct": 16.1616,
    "BBpct": 5.7239,
    "KBB": 2.82,
    "IP": 47.1,
    "HR9": 1.1,
    "FIP": 4.08,
    "W": 1,
    "L": 3
  },
  {
    "Player": "Justus Sheffield",
    "Season": 2020,
    "ERA": 3.58,
    "WHIP": 1.301,
    "Kpct": 16.1616,
    "BBpct": 6.734,
    "KBB": 2.4,
    "IP": 55.1,
    "HR9": 0.3,
    "FIP": 3.17,
    "W": 4,
    "L": 3
  },
  {
    "Player": "Yusei Kikuchi",
    "Season": 2020,
    "ERA": 5.17,
    "WHIP": 1.298,
    "Kpct": 15.8249,
    "BBpct": 6.734,
    "KBB": 2.35,
    "IP": 47,
    "HR9": 0.6,
    "FIP": 3.3,
    "W": 2,
    "L": 4
  },
  {
    "Player": "Seth Lugo",
    "Season": 2020,
    "ERA": 5.15,
    "WHIP": 1.364,
    "Kpct": 15.8249,
    "BBpct": 3.367,
    "KBB": 4.7,
    "IP": 36.2,
    "HR9": 2,
    "FIP": 4.45,
    "W": 3,
    "L": 4
  },
  {
    "Player": "Jordan Montgomery",
    "Season": 2020,
    "ERA": 5.11,
    "WHIP": 1.295,
    "Kpct": 15.8249,
    "BBpct": 3.0303,
    "KBB": 5.22,
    "IP": 44,
    "HR9": 1.4,
    "FIP": 3.87,
    "W": 2,
    "L": 3
  },
  {
    "Player": "Freddy Peralta",
    "Season": 2020,
    "ERA": 3.99,
    "WHIP": 1.159,
    "Kpct": 15.8249,
    "BBpct": 4.0404,
    "KBB": 3.92,
    "IP": 29.1,
    "HR9": 0.6,
    "FIP": 2.41,
    "W": 3,
    "L": 1
  },
  {
    "Player": "Kyle Freeland",
    "Season": 2020,
    "ERA": 4.33,
    "WHIP": 1.415,
    "Kpct": 15.4882,
    "BBpct": 7.7441,
    "KBB": 2,
    "IP": 70.2,
    "HR9": 1.1,
    "FIP": 4.65,
    "W": 2,
    "L": 3
  },
  {
    "Player": "Tony Gonsolin",
    "Season": 2020,
    "ERA": 2.31,
    "WHIP": 0.836,
    "Kpct": 15.4882,
    "BBpct": 2.3569,
    "KBB": 6.57,
    "IP": 46.2,
    "HR9": 0.4,
    "FIP": 2.29,
    "W": 2,
    "L": 2
  },
  {
    "Player": "Alec Mills",
    "Season": 2020,
    "ERA": 4.48,
    "WHIP": 1.155,
    "Kpct": 15.4882,
    "BBpct": 6.3973,
    "KBB": 2.42,
    "IP": 62.1,
    "HR9": 1.9,
    "FIP": 5.44,
    "W": 5,
    "L": 5
  },
  {
    "Player": "Martín Pérez",
    "Season": 2020,
    "ERA": 4.5,
    "WHIP": 1.339,
    "Kpct": 15.4882,
    "BBpct": 9.4276,
    "KBB": 1.64,
    "IP": 62,
    "HR9": 1.2,
    "FIP": 4.88,
    "W": 3,
    "L": 5
  },
  {
    "Player": "Garrett Richards",
    "Season": 2020,
    "ERA": 4.03,
    "WHIP": 1.247,
    "Kpct": 15.4882,
    "BBpct": 5.7239,
    "KBB": 2.71,
    "IP": 51.1,
    "HR9": 1.2,
    "FIP": 4.28,
    "W": 2,
    "L": 2
  },
  {
    "Player": "Vince Velasquez",
    "Season": 2020,
    "ERA": 5.56,
    "WHIP": 1.559,
    "Kpct": 15.4882,
    "BBpct": 5.7239,
    "KBB": 2.71,
    "IP": 34,
    "HR9": 1.3,
    "FIP": 4.16,
    "W": 1,
    "L": 1
  },
  {
    "Player": "Logan Webb",
    "Season": 2020,
    "ERA": 5.47,
    "WHIP": 1.564,
    "Kpct": 15.4882,
    "BBpct": 8.0808,
    "KBB": 1.92,
    "IP": 54.1,
    "HR9": 0.7,
    "FIP": 4.17,
    "W": 3,
    "L": 4
  },
  {
    "Player": "Tejay Antone",
    "Season": 2020,
    "ERA": 2.8,
    "WHIP": 1.019,
    "Kpct": 15.1515,
    "BBpct": 5.3872,
    "KBB": 2.81,
    "IP": 35.1,
    "HR9": 1,
    "FIP": 3.64,
    "W": 0,
    "L": 3
  },
  {
    "Player": "Derek Holland",
    "Season": 2020,
    "ERA": 6.86,
    "WHIP": 1.402,
    "Kpct": 15.1515,
    "BBpct": 5.0505,
    "KBB": 3,
    "IP": 40.2,
    "HR9": 2.7,
    "FIP": 6.14,
    "W": 1,
    "L": 3
  },
  {
    "Player": "Sean Manaea",
    "Season": 2020,
    "ERA": 4.5,
    "WHIP": 1.204,
    "Kpct": 15.1515,
    "BBpct": 2.6936,
    "KBB": 5.63,
    "IP": 54,
    "HR9": 1.2,
    "FIP": 3.71,
    "W": 4,
    "L": 3
  },
  {
    "Player": "Daniel Ponce de Leon",
    "Season": 2020,
    "ERA": 4.96,
    "WHIP": 1.316,
    "Kpct": 15.1515,
    "BBpct": 6.734,
    "KBB": 2.25,
    "IP": 32.2,
    "HR9": 2.2,
    "FIP": 5.64,
    "W": 1,
    "L": 3
  },
  {
    "Player": "Julio Urías",
    "Season": 2020,
    "ERA": 3.27,
    "WHIP": 1.145,
    "Kpct": 15.1515,
    "BBpct": 6.0606,
    "KBB": 2.5,
    "IP": 55,
    "HR9": 0.8,
    "FIP": 3.72,
    "W": 3,
    "L": 0
  },
  {
    "Player": "Dylan Cease",
    "Season": 2020,
    "ERA": 4.01,
    "WHIP": 1.44,
    "Kpct": 14.8148,
    "BBpct": 11.4478,
    "KBB": 1.29,
    "IP": 58.1,
    "HR9": 1.9,
    "FIP": 6.36,
    "W": 5,
    "L": 4
  },
  {
    "Player": "Adrian Houser",
    "Season": 2020,
    "ERA": 5.3,
    "WHIP": 1.5,
    "Kpct": 14.8148,
    "BBpct": 7.0707,
    "KBB": 2.1,
    "IP": 56,
    "HR9": 1.3,
    "FIP": 4.82,
    "W": 1,
    "L": 6
  },
  {
    "Player": "Chad Kuhl",
    "Season": 2020,
    "ERA": 4.27,
    "WHIP": 1.36,
    "Kpct": 14.8148,
    "BBpct": 9.4276,
    "KBB": 1.57,
    "IP": 46.1,
    "HR9": 1.6,
    "FIP": 5.48,
    "W": 2,
    "L": 3
  },
  {
    "Player": "Dustin May",
    "Season": 2020,
    "ERA": 2.57,
    "WHIP": 1.089,
    "Kpct": 14.8148,
    "BBpct": 5.3872,
    "KBB": 2.75,
    "IP": 56,
    "HR9": 1.4,
    "FIP": 4.62,
    "W": 3,
    "L": 1
  },
  {
    "Player": "Masahiro Tanaka",
    "Season": 2020,
    "ERA": 3.56,
    "WHIP": 1.167,
    "Kpct": 14.8148,
    "BBpct": 2.6936,
    "KBB": 5.5,
    "IP": 48,
    "HR9": 1.7,
    "FIP": 4.42,
    "W": 3,
    "L": 3
  },
  {
    "Player": "Austin Voth",
    "Season": 2020,
    "ERA": 6.34,
    "WHIP": 1.51,
    "Kpct": 14.8148,
    "BBpct": 6.0606,
    "KBB": 2.44,
    "IP": 49.2,
    "HR9": 2.5,
    "FIP": 6.41,
    "W": 2,
    "L": 5
  },
  {
    "Player": "Ryan Yarbrough",
    "Season": 2020,
    "ERA": 3.56,
    "WHIP": 1.186,
    "Kpct": 14.8148,
    "BBpct": 4.0404,
    "KBB": 3.67,
    "IP": 55.2,
    "HR9": 0.8,
    "FIP": 3.8,
    "W": 1,
    "L": 4
  },
  {
    "Player": "Tyler Matzek",
    "Season": 2020,
    "ERA": 2.79,
    "WHIP": 1.138,
    "Kpct": 14.4781,
    "BBpct": 3.367,
    "KBB": 4.3,
    "IP": 29,
    "HR9": 0.3,
    "FIP": 1.92,
    "W": 4,
    "L": 3
  },
  {
    "Player": "Mike Mayers",
    "Season": 2020,
    "ERA": 2.1,
    "WHIP": 0.9,
    "Kpct": 14.4781,
    "BBpct": 3.0303,
    "KBB": 4.78,
    "IP": 30,
    "HR9": 0.6,
    "FIP": 2.19,
    "W": 2,
    "L": 0
  },
  {
    "Player": "Aníbal Sánchez",
    "Season": 2020,
    "ERA": 6.62,
    "WHIP": 1.66,
    "Kpct": 14.4781,
    "BBpct": 6.0606,
    "KBB": 2.39,
    "IP": 53,
    "HR9": 1.9,
    "FIP": 5.46,
    "W": 4,
    "L": 5
  },
  {
    "Player": "Walker Buehler",
    "Season": 2020,
    "ERA": 3.44,
    "WHIP": 0.955,
    "Kpct": 14.1414,
    "BBpct": 3.7037,
    "KBB": 3.82,
    "IP": 36.2,
    "HR9": 1.7,
    "FIP": 4.36,
    "W": 1,
    "L": 0
  },
  {
    "Player": "J.A. Happ",
    "Season": 2020,
    "ERA": 3.47,
    "WHIP": 1.054,
    "Kpct": 14.1414,
    "BBpct": 5.0505,
    "KBB": 2.8,
    "IP": 49.1,
    "HR9": 1.5,
    "FIP": 4.57,
    "W": 2,
    "L": 2
  },
  {
    "Player": "Dallas Keuchel",
    "Season": 2020,
    "ERA": 1.99,
    "WHIP": 1.089,
    "Kpct": 14.1414,
    "BBpct": 5.7239,
    "KBB": 2.47,
    "IP": 63.1,
    "HR9": 0.3,
    "FIP": 3.08,
    "W": 6,
    "L": 2
  },
  {
    "Player": "Jon Lester",
    "Season": 2020,
    "ERA": 5.16,
    "WHIP": 1.328,
    "Kpct": 14.1414,
    "BBpct": 5.7239,
    "KBB": 2.47,
    "IP": 61,
    "HR9": 1.6,
    "FIP": 5.14,
    "W": 3,
    "L": 3
  },
  {
    "Player": "Triston McKenzie",
    "Season": 2020,
    "ERA": 3.24,
    "WHIP": 0.9,
    "Kpct": 14.1414,
    "BBpct": 3.0303,
    "KBB": 4.67,
    "IP": 33.1,
    "HR9": 1.6,
    "FIP": 3.91,
    "W": 2,
    "L": 1
  },
  {
    "Player": "John Means",
    "Season": 2020,
    "ERA": 4.53,
    "WHIP": 0.985,
    "Kpct": 14.1414,
    "BBpct": 2.3569,
    "KBB": 6,
    "IP": 43.2,
    "HR9": 2.5,
    "FIP": 5.6,
    "W": 2,
    "L": 4
  },
  {
    "Player": "Charlie Morton",
    "Season": 2020,
    "ERA": 4.74,
    "WHIP": 1.395,
    "Kpct": 14.1414,
    "BBpct": 3.367,
    "KBB": 4.2,
    "IP": 38,
    "HR9": 0.9,
    "FIP": 3.45,
    "W": 2,
    "L": 2
  },
  {
    "Player": "Drew Smyly",
    "Season": 2020,
    "ERA": 3.42,
    "WHIP": 1.101,
    "Kpct": 14.1414,
    "BBpct": 3.0303,
    "KBB": 4.67,
    "IP": 26.1,
    "HR9": 0.7,
    "FIP": 2.01,
    "W": 0,
    "L": 1
  },
  {
    "Player": "Ian Anderson",
    "Season": 2020,
    "ERA": 1.95,
    "WHIP": 1.082,
    "Kpct": 13.8047,
    "BBpct": 4.7138,
    "KBB": 2.93,
    "IP": 32.1,
    "HR9": 0.3,
    "FIP": 2.54,
    "W": 3,
    "L": 2
  },
  {
    "Player": "Tyler Anderson",
    "Season": 2020,
    "ERA": 4.37,
    "WHIP": 1.391,
    "Kpct": 13.8047,
    "BBpct": 8.4175,
    "KBB": 1.64,
    "IP": 59.2,
    "HR9": 0.8,
    "FIP": 4.36,
    "W": 4,
    "L": 3
  },
  {
    "Player": "Tanner Roark",
    "Season": 2020,
    "ERA": 6.8,
    "WHIP": 1.741,
    "Kpct": 13.8047,
    "BBpct": 7.7441,
    "KBB": 1.78,
    "IP": 47.2,
    "HR9": 2.6,
    "FIP": 6.86,
    "W": 2,
    "L": 3
  },
  {
    "Player": "Antonio Senzatela",
    "Season": 2020,
    "ERA": 3.44,
    "WHIP": 1.214,
    "Kpct": 13.8047,
    "BBpct": 6.0606,
    "KBB": 2.28,
    "IP": 73.1,
    "HR9": 1.1,
    "FIP": 4.57,
    "W": 5,
    "L": 3
  },
  {
    "Player": "Taylor Clarke",
    "Season": 2020,
    "ERA": 4.36,
    "WHIP": 1.292,
    "Kpct": 13.468,
    "BBpct": 7.0707,
    "KBB": 1.9,
    "IP": 43.1,
    "HR9": 1.7,
    "FIP": 5.2,
    "W": 3,
    "L": 0
  },
  {
    "Player": "Mike Clevinger",
    "Season": 2020,
    "ERA": 3.02,
    "WHIP": 1.152,
    "Kpct": 13.468,
    "BBpct": 4.7138,
    "KBB": 2.86,
    "IP": 41.2,
    "HR9": 1.3,
    "FIP": 4.15,
    "W": 3,
    "L": 2
  },
  {
    "Player": "Tommy Milone",
    "Season": 2020,
    "ERA": 6.69,
    "WHIP": 1.564,
    "Kpct": 13.468,
    "BBpct": 2.0202,
    "KBB": 6.67,
    "IP": 39,
    "HR9": 2.1,
    "FIP": 4.76,
    "W": 1,
    "L": 4
  },
  {
    "Player": "David Peterson",
    "Season": 2020,
    "ERA": 3.44,
    "WHIP": 1.208,
    "Kpct": 13.468,
    "BBpct": 8.0808,
    "KBB": 1.67,
    "IP": 49.2,
    "HR9": 0.9,
    "FIP": 4.52,
    "W": 6,
    "L": 2
  },
  {
    "Player": "Ross Stripling",
    "Season": 2020,
    "ERA": 5.84,
    "WHIP": 1.5,
    "Kpct": 13.468,
    "BBpct": 6.0606,
    "KBB": 2.22,
    "IP": 49.1,
    "HR9": 2.4,
    "FIP": 6.15,
    "W": 3,
    "L": 3
  },
  {
    "Player": "Sandy Alcantara",
    "Season": 2020,
    "ERA": 3,
    "WHIP": 1.19,
    "Kpct": 13.1313,
    "BBpct": 5.0505,
    "KBB": 2.6,
    "IP": 42,
    "HR9": 0.9,
    "FIP": 3.71,
    "W": 3,
    "L": 2
  },
  {
    "Player": "Scott Barlow",
    "Season": 2020,
    "ERA": 4.2,
    "WHIP": 1.2,
    "Kpct": 13.1313,
    "BBpct": 3.0303,
    "KBB": 4.33,
    "IP": 30,
    "HR9": 1.2,
    "FIP": 3.42,
    "W": 2,
    "L": 1
  },
  {
    "Player": "Pete Fairbanks",
    "Season": 2020,
    "ERA": 2.7,
    "WHIP": 1.388,
    "Kpct": 13.1313,
    "BBpct": 4.7138,
    "KBB": 2.79,
    "IP": 26.2,
    "HR9": 0.7,
    "FIP": 3.04,
    "W": 6,
    "L": 3
  },
  {
    "Player": "Trevor Rogers",
    "Season": 2020,
    "ERA": 6.11,
    "WHIP": 1.607,
    "Kpct": 13.1313,
    "BBpct": 4.3771,
    "KBB": 3,
    "IP": 28,
    "HR9": 1.6,
    "FIP": 4.33,
    "W": 1,
    "L": 2
  },
  {
    "Player": "Chris Stratton",
    "Season": 2020,
    "ERA": 3.9,
    "WHIP": 1.3,
    "Kpct": 13.1313,
    "BBpct": 4.3771,
    "KBB": 3,
    "IP": 30,
    "HR9": 0.9,
    "FIP": 3.19,
    "W": 2,
    "L": 1
  },
  {
    "Player": "Alex Young",
    "Season": 2020,
    "ERA": 5.44,
    "WHIP": 1.403,
    "Kpct": 13.1313,
    "BBpct": 4.7138,
    "KBB": 2.79,
    "IP": 46.1,
    "HR9": 2.1,
    "FIP": 5.57,
    "W": 2,
    "L": 4
  },
  {
    "Player": "Chase Anderson",
    "Season": 2020,
    "ERA": 7.22,
    "WHIP": 1.634,
    "Kpct": 12.7946,
    "BBpct": 3.367,
    "KBB": 3.8,
    "IP": 33.2,
    "HR9": 2.9,
    "FIP": 6.16,
    "W": 1,
    "L": 2
  },
  {
    "Player": "Steven Brault",
    "Season": 2020,
    "ERA": 3.38,
    "WHIP": 1.195,
    "Kpct": 12.7946,
    "BBpct": 7.4074,
    "KBB": 1.73,
    "IP": 42.2,
    "HR9": 0.4,
    "FIP": 3.92,
    "W": 1,
    "L": 3
  },
  {
    "Player": "Miguel Castro",
    "Season": 2020,
    "ERA": 4.01,
    "WHIP": 1.662,
    "Kpct": 12.7946,
    "BBpct": 4.3771,
    "KBB": 2.92,
    "IP": 24.2,
    "HR9": 1.5,
    "FIP": 3.92,
    "W": 2,
    "L": 2
  },
  {
    "Player": "Alex Cobb",
    "Season": 2020,
    "ERA": 4.3,
    "WHIP": 1.338,
    "Kpct": 12.7946,
    "BBpct": 6.0606,
    "KBB": 2.11,
    "IP": 52.1,
    "HR9": 1.4,
    "FIP": 4.87,
    "W": 2,
    "L": 5
  },
  {
    "Player": "Justin Dunn",
    "Season": 2020,
    "ERA": 4.34,
    "WHIP": 1.358,
    "Kpct": 12.7946,
    "BBpct": 10.4377,
    "KBB": 1.23,
    "IP": 45.2,
    "HR9": 2,
    "FIP": 6.54,
    "W": 4,
    "L": 1
  },
  {
    "Player": "Trevor May",
    "Season": 2020,
    "ERA": 3.86,
    "WHIP": 1.157,
    "Kpct": 12.7946,
    "BBpct": 2.3569,
    "KBB": 5.43,
    "IP": 23.1,
    "HR9": 1.9,
    "FIP": 3.62,
    "W": 1,
    "L": 0
  },
  {
    "Player": "Trevor Rosenthal",
    "Season": 2020,
    "ERA": 1.9,
    "WHIP": 0.845,
    "Kpct": 12.7946,
    "BBpct": 2.6936,
    "KBB": 4.75,
    "IP": 23.2,
    "HR9": 0.8,
    "FIP": 2.22,
    "W": 1,
    "L": 0
  },
  {
    "Player": "Brent Suter",
    "Season": 2020,
    "ERA": 3.13,
    "WHIP": 1.105,
    "Kpct": 12.7946,
    "BBpct": 1.6835,
    "KBB": 7.6,
    "IP": 31.2,
    "HR9": 1.1,
    "FIP": 3,
    "W": 2,
    "L": 0
  },
  {
    "Player": "Mike Fiers",
    "Season": 2020,
    "ERA": 4.58,
    "WHIP": 1.373,
    "Kpct": 12.4579,
    "BBpct": 5.3872,
    "KBB": 2.31,
    "IP": 59,
    "HR9": 1.4,
    "FIP": 4.94,
    "W": 6,
    "L": 3
  },
  {
    "Player": "Liam Hendriks",
    "Season": 2020,
    "ERA": 1.78,
    "WHIP": 0.671,
    "Kpct": 12.4579,
    "BBpct": 1.0101,
    "KBB": 12.33,
    "IP": 25.1,
    "HR9": 0.4,
    "FIP": 1.14,
    "W": 3,
    "L": 1
  },
  {
    "Player": "Tarik Skubal",
    "Season": 2020,
    "ERA": 5.63,
    "WHIP": 1.219,
    "Kpct": 12.4579,
    "BBpct": 3.7037,
    "KBB": 3.36,
    "IP": 32,
    "HR9": 2.5,
    "FIP": 5.75,
    "W": 1,
    "L": 4
  },
  {
    "Player": "Josh Staumont",
    "Season": 2020,
    "ERA": 2.45,
    "WHIP": 1.403,
    "Kpct": 12.4579,
    "BBpct": 5.3872,
    "KBB": 2.31,
    "IP": 25.2,
    "HR9": 0.7,
    "FIP": 3.54,
    "W": 2,
    "L": 1
  },
  {
    "Player": "Michael Wacha",
    "Season": 2020,
    "ERA": 6.62,
    "WHIP": 1.559,
    "Kpct": 12.4579,
    "BBpct": 2.3569,
    "KBB": 5.29,
    "IP": 34,
    "HR9": 2.4,
    "FIP": 5.25,
    "W": 1,
    "L": 4
  },
  {
    "Player": "Jordan Lyles",
    "Season": 2020,
    "ERA": 7.02,
    "WHIP": 1.561,
    "Kpct": 12.1212,
    "BBpct": 7.7441,
    "KBB": 1.57,
    "IP": 57.2,
    "HR9": 1.9,
    "FIP": 5.95,
    "W": 1,
    "L": 6
  },
  {
    "Player": "Nick Margevicius",
    "Season": 2020,
    "ERA": 4.57,
    "WHIP": 1.258,
    "Kpct": 12.1212,
    "BBpct": 4.7138,
    "KBB": 2.57,
    "IP": 41.1,
    "HR9": 1.3,
    "FIP": 4.35,
    "W": 2,
    "L": 3
  },
  {
    "Player": "Steven Matz",
    "Season": 2020,
    "ERA": 9.68,
    "WHIP": 1.696,
    "Kpct": 12.1212,
    "BBpct": 3.367,
    "KBB": 3.6,
    "IP": 30.2,
    "HR9": 4.1,
    "FIP": 7.76,
    "W": 0,
    "L": 5
  },
  {
    "Player": "Josh Tomlin",
    "Season": 2020,
    "ERA": 4.76,
    "WHIP": 1.21,
    "Kpct": 12.1212,
    "BBpct": 2.6936,
    "KBB": 4.5,
    "IP": 39.2,
    "HR9": 1.4,
    "FIP": 4.02,
    "W": 2,
    "L": 2
  },
  {
    "Player": "Keegan Akin",
    "Season": 2020,
    "ERA": 4.56,
    "WHIP": 1.442,
    "Kpct": 11.7845,
    "BBpct": 3.367,
    "KBB": 3.5,
    "IP": 25.2,
    "HR9": 1.1,
    "FIP": 3.27,
    "W": 1,
    "L": 2
  },
  {
    "Player": "Dane Dunning",
    "Season": 2020,
    "ERA": 3.97,
    "WHIP": 1.118,
    "Kpct": 11.7845,
    "BBpct": 4.3771,
    "KBB": 2.69,
    "IP": 34,
    "HR9": 1.1,
    "FIP": 3.99,
    "W": 2,
    "L": 0
  },
  {
    "Player": "Brad Keller",
    "Season": 2020,
    "ERA": 2.47,
    "WHIP": 1.024,
    "Kpct": 11.7845,
    "BBpct": 5.7239,
    "KBB": 2.06,
    "IP": 54.2,
    "HR9": 0.3,
    "FIP": 3.43,
    "W": 5,
    "L": 3
  },
  {
    "Player": "Michael Lorenzen",
    "Season": 2020,
    "ERA": 4.28,
    "WHIP": 1.396,
    "Kpct": 11.7845,
    "BBpct": 5.7239,
    "KBB": 2.06,
    "IP": 33.2,
    "HR9": 0.8,
    "FIP": 3.87,
    "W": 3,
    "L": 1
  },
  {
    "Player": "Matt Wisler",
    "Season": 2020,
    "ERA": 1.07,
    "WHIP": 1.145,
    "Kpct": 11.7845,
    "BBpct": 4.7138,
    "KBB": 2.5,
    "IP": 25.1,
    "HR9": 0.7,
    "FIP": 3.35,
    "W": 0,
    "L": 1
  },
  {
    "Player": "Tyler Alexander",
    "Season": 2020,
    "ERA": 3.96,
    "WHIP": 1.321,
    "Kpct": 11.4478,
    "BBpct": 3.0303,
    "KBB": 3.78,
    "IP": 36.1,
    "HR9": 2,
    "FIP": 5.26,
    "W": 2,
    "L": 3
  },
  {
    "Player": "José Cisnero",
    "Season": 2020,
    "ERA": 3.03,
    "WHIP": 1.112,
    "Kpct": 11.4478,
    "BBpct": 3.367,
    "KBB": 3.4,
    "IP": 29.2,
    "HR9": 0.3,
    "FIP": 2.65,
    "W": 3,
    "L": 3
  },
  {
    "Player": "Gio González",
    "Season": 2020,
    "ERA": 4.83,
    "WHIP": 1.863,
    "Kpct": 11.4478,
    "BBpct": 6.3973,
    "KBB": 1.79,
    "IP": 31.2,
    "HR9": 1.7,
    "FIP": 5.5,
    "W": 1,
    "L": 2
  },
  {
    "Player": "Elieser Hernández",
    "Season": 2020,
    "ERA": 3.16,
    "WHIP": 1.013,
    "Kpct": 11.4478,
    "BBpct": 1.6835,
    "KBB": 6.8,
    "IP": 25.2,
    "HR9": 1.8,
    "FIP": 3.89,
    "W": 1,
    "L": 0
  },
  {
    "Player": "Richard Rodríguez",
    "Season": 2020,
    "ERA": 2.7,
    "WHIP": 0.857,
    "Kpct": 11.4478,
    "BBpct": 1.6835,
    "KBB": 6.8,
    "IP": 23.1,
    "HR9": 1.2,
    "FIP": 2.85,
    "W": 3,
    "L": 2
  },
  {
    "Player": "Chasen Shreve",
    "Season": 2020,
    "ERA": 3.96,
    "WHIP": 1.16,
    "Kpct": 11.4478,
    "BBpct": 4.0404,
    "KBB": 2.83,
    "IP": 25,
    "HR9": 1.4,
    "FIP": 3.99,
    "W": 1,
    "L": 0
  },
  {
    "Player": "Lucas Sims",
    "Season": 2020,
    "ERA": 2.45,
    "WHIP": 0.935,
    "Kpct": 11.4478,
    "BBpct": 3.7037,
    "KBB": 3.09,
    "IP": 25.2,
    "HR9": 1.1,
    "FIP": 3.7,
    "W": 3,
    "L": 0
  },
  {
    "Player": "Matt Andriese",
    "Season": 2020,
    "ERA": 4.5,
    "WHIP": 1,
    "Kpct": 11.1111,
    "BBpct": 3.7037,
    "KBB": 3,
    "IP": 32,
    "HR9": 1.4,
    "FIP": 4.28,
    "W": 2,
    "L": 4
  },
  {
    "Player": "Deivi García",
    "Season": 2020,
    "ERA": 4.98,
    "WHIP": 1.194,
    "Kpct": 11.1111,
    "BBpct": 2.0202,
    "KBB": 5.5,
    "IP": 34.1,
    "HR9": 1.6,
    "FIP": 4.15,
    "W": 3,
    "L": 2
  },
  {
    "Player": "Kenley Jansen",
    "Season": 2020,
    "ERA": 3.33,
    "WHIP": 1.151,
    "Kpct": 11.1111,
    "BBpct": 3.0303,
    "KBB": 3.67,
    "IP": 24.1,
    "HR9": 0.7,
    "FIP": 3.03,
    "W": 3,
    "L": 1
  },
  {
    "Player": "Jake McGee",
    "Season": 2020,
    "ERA": 2.66,
    "WHIP": 0.836,
    "Kpct": 11.1111,
    "BBpct": 1.0101,
    "KBB": 11,
    "IP": 20.1,
    "HR9": 0.9,
    "FIP": 1.67,
    "W": 3,
    "L": 1
  },
  {
    "Player": "Sixto Sánchez",
    "Season": 2020,
    "ERA": 3.46,
    "WHIP": 1.205,
    "Kpct": 11.1111,
    "BBpct": 3.7037,
    "KBB": 3,
    "IP": 39,
    "HR9": 0.7,
    "FIP": 3.5,
    "W": 3,
    "L": 2
  },
  {
    "Player": "Patrick Sandoval",
    "Season": 2020,
    "ERA": 5.65,
    "WHIP": 1.336,
    "Kpct": 11.1111,
    "BBpct": 4.0404,
    "KBB": 2.75,
    "IP": 36.2,
    "HR9": 2.5,
    "FIP": 5.92,
    "W": 1,
    "L": 5
  },
  {
    "Player": "Kolby Allard",
    "Season": 2020,
    "ERA": 7.75,
    "WHIP": 1.515,
    "Kpct": 10.7744,
    "BBpct": 6.734,
    "KBB": 1.6,
    "IP": 33.2,
    "HR9": 1.1,
    "FIP": 4.71,
    "W": 0,
    "L": 6
  },
  {
    "Player": "Brett Anderson",
    "Season": 2020,
    "ERA": 4.21,
    "WHIP": 1.277,
    "Kpct": 10.7744,
    "BBpct": 3.367,
    "KBB": 3.2,
    "IP": 47,
    "HR9": 1.1,
    "FIP": 4.38,
    "W": 4,
    "L": 4
  },
  {
    "Player": "Jake Arrieta",
    "Season": 2020,
    "ERA": 5.08,
    "WHIP": 1.511,
    "Kpct": 10.7744,
    "BBpct": 5.3872,
    "KBB": 2,
    "IP": 44.1,
    "HR9": 1.2,
    "FIP": 4.66,
    "W": 4,
    "L": 4
  },
  {
    "Player": "Génesis Cabrera",
    "Season": 2020,
    "ERA": 2.42,
    "WHIP": 1.164,
    "Kpct": 10.7744,
    "BBpct": 5.3872,
    "KBB": 2,
    "IP": 22.1,
    "HR9": 1.2,
    "FIP": 4.76,
    "W": 4,
    "L": 1
  },
  {
    "Player": "Grant Dayton",
    "Season": 2020,
    "ERA": 2.3,
    "WHIP": 1.207,
    "Kpct": 10.7744,
    "BBpct": 3.7037,
    "KBB": 2.91,
    "IP": 27.1,
    "HR9": 1.3,
    "FIP": 4.07,
    "W": 2,
    "L": 1
  },
  {
    "Player": "Chad Green",
    "Season": 2020,
    "ERA": 3.51,
    "WHIP": 0.818,
    "Kpct": 10.7744,
    "BBpct": 2.6936,
    "KBB": 4,
    "IP": 25.2,
    "HR9": 1.8,
    "FIP": 4.17,
    "W": 3,
    "L": 3
  },
  {
    "Player": "Phil Maton",
    "Season": 2020,
    "ERA": 4.57,
    "WHIP": 1.338,
    "Kpct": 10.7744,
    "BBpct": 2.0202,
    "KBB": 5.33,
    "IP": 21.2,
    "HR9": 0.4,
    "FIP": 2.22,
    "W": 3,
    "L": 3
  },
  {
    "Player": "Tanner Rainey",
    "Season": 2020,
    "ERA": 2.66,
    "WHIP": 0.738,
    "Kpct": 10.7744,
    "BBpct": 2.3569,
    "KBB": 4.57,
    "IP": 20.1,
    "HR9": 1.8,
    "FIP": 3.78,
    "W": 1,
    "L": 1
  },
  {
    "Player": "Matt Barnes",
    "Season": 2020,
    "ERA": 4.3,
    "WHIP": 1.391,
    "Kpct": 10.4377,
    "BBpct": 4.7138,
    "KBB": 2.21,
    "IP": 23,
    "HR9": 1.6,
    "FIP": 4.84,
    "W": 1,
    "L": 3
  },
  {
    "Player": "Trevor Cahill",
    "Season": 2020,
    "ERA": 3.24,
    "WHIP": 1.2,
    "Kpct": 10.4377,
    "BBpct": 4.7138,
    "KBB": 2.21,
    "IP": 25,
    "HR9": 1.1,
    "FIP": 4.19,
    "W": 1,
    "L": 2
  },
  {
    "Player": "Jake Diekman",
    "Season": 2020,
    "ERA": 0.42,
    "WHIP": 0.938,
    "Kpct": 10.4377,
    "BBpct": 4.0404,
    "KBB": 2.58,
    "IP": 21.1,
    "HR9": 0.4,
    "FIP": 2.72,
    "W": 2,
    "L": 0
  },
  {
    "Player": "Rafael Dolis",
    "Season": 2020,
    "ERA": 1.5,
    "WHIP": 1.25,
    "Kpct": 10.4377,
    "BBpct": 4.7138,
    "KBB": 2.21,
    "IP": 24,
    "HR9": 0.4,
    "FIP": 3.02,
    "W": 2,
    "L": 2
  },
  {
    "Player": "Tyler Duffey",
    "Season": 2020,
    "ERA": 1.88,
    "WHIP": 0.792,
    "Kpct": 10.4377,
    "BBpct": 2.0202,
    "KBB": 5.17,
    "IP": 24,
    "HR9": 0.8,
    "FIP": 2.57,
    "W": 1,
    "L": 1
  },
  {
    "Player": "Matt Foster",
    "Season": 2020,
    "ERA": 2.2,
    "WHIP": 0.872,
    "Kpct": 10.4377,
    "BBpct": 3.0303,
    "KBB": 3.44,
    "IP": 28.2,
    "HR9": 0.6,
    "FIP": 2.88,
    "W": 6,
    "L": 1
  },
  {
    "Player": "Josh Hader",
    "Season": 2020,
    "ERA": 3.79,
    "WHIP": 0.947,
    "Kpct": 10.4377,
    "BBpct": 3.367,
    "KBB": 3.1,
    "IP": 19,
    "HR9": 1.4,
    "FIP": 4.03,
    "W": 1,
    "L": 2
  },
  {
    "Player": "Jonathan Hernández",
    "Season": 2020,
    "ERA": 2.9,
    "WHIP": 1.032,
    "Kpct": 10.4377,
    "BBpct": 2.6936,
    "KBB": 3.88,
    "IP": 31,
    "HR9": 0.6,
    "FIP": 3.19,
    "W": 5,
    "L": 1
  },
  {
    "Player": "Rich Hill",
    "Season": 2020,
    "ERA": 3.03,
    "WHIP": 1.164,
    "Kpct": 10.4377,
    "BBpct": 5.7239,
    "KBB": 1.82,
    "IP": 38.2,
    "HR9": 0.7,
    "FIP": 3.99,
    "W": 2,
    "L": 2
  },
  {
    "Player": "Greg Holland",
    "Season": 2020,
    "ERA": 1.91,
    "WHIP": 0.953,
    "Kpct": 10.4377,
    "BBpct": 2.3569,
    "KBB": 4.43,
    "IP": 28.1,
    "HR9": 0.3,
    "FIP": 2.52,
    "W": 3,
    "L": 0
  },
  {
    "Player": "Dakota Hudson",
    "Season": 2020,
    "ERA": 2.77,
    "WHIP": 1,
    "Kpct": 10.4377,
    "BBpct": 5.0505,
    "KBB": 2.07,
    "IP": 39,
    "HR9": 1.2,
    "FIP": 4.5,
    "W": 3,
    "L": 2
  },
  {
    "Player": "Raisel Iglesias",
    "Season": 2020,
    "ERA": 2.74,
    "WHIP": 0.913,
    "Kpct": 10.4377,
    "BBpct": 1.6835,
    "KBB": 6.2,
    "IP": 23,
    "HR9": 0.4,
    "FIP": 1.84,
    "W": 4,
    "L": 3
  },
  {
    "Player": "David Phelps",
    "Season": 2020,
    "ERA": 6.53,
    "WHIP": 1.161,
    "Kpct": 10.4377,
    "BBpct": 1.6835,
    "KBB": 6.2,
    "IP": 20.2,
    "HR9": 3,
    "FIP": 5.47,
    "W": 2,
    "L": 4
  },
  {
    "Player": "Cal Quantrill",
    "Season": 2020,
    "ERA": 2.25,
    "WHIP": 1.219,
    "Kpct": 10.4377,
    "BBpct": 2.6936,
    "KBB": 3.88,
    "IP": 32,
    "HR9": 1.1,
    "FIP": 3.91,
    "W": 2,
    "L": 0
  },
  {
    "Player": "Ryan Tepera",
    "Season": 2020,
    "ERA": 3.92,
    "WHIP": 1.403,
    "Kpct": 10.4377,
    "BBpct": 4.0404,
    "KBB": 2.58,
    "IP": 20.2,
    "HR9": 0.9,
    "FIP": 3.34,
    "W": 0,
    "L": 1
  },
  {
    "Player": "J.B. Wendelken",
    "Season": 2020,
    "ERA": 1.8,
    "WHIP": 1.12,
    "Kpct": 10.4377,
    "BBpct": 3.7037,
    "KBB": 2.82,
    "IP": 25,
    "HR9": 0.7,
    "FIP": 3.07,
    "W": 1,
    "L": 1
  },
  {
    "Player": "Asher Wojciechowski",
    "Season": 2020,
    "ERA": 6.81,
    "WHIP": 1.622,
    "Kpct": 10.4377,
    "BBpct": 5.0505,
    "KBB": 2.07,
    "IP": 37,
    "HR9": 2.7,
    "FIP": 6.68,
    "W": 1,
    "L": 3
  },
  {
    "Player": "Ryan Brasier",
    "Season": 2020,
    "ERA": 3.96,
    "WHIP": 1.4,
    "Kpct": 10.101,
    "BBpct": 3.7037,
    "KBB": 2.73,
    "IP": 25,
    "HR9": 0.7,
    "FIP": 3.15,
    "W": 1,
    "L": 0
  },
  {
    "Player": "Madison Bumgarner",
    "Season": 2020,
    "ERA": 6.48,
    "WHIP": 1.44,
    "Kpct": 10.101,
    "BBpct": 4.3771,
    "KBB": 2.31,
    "IP": 41.2,
    "HR9": 2.8,
    "FIP": 7.18,
    "W": 1,
    "L": 4
  },
  {
    "Player": "Evan Marshall",
    "Season": 2020,
    "ERA": 2.38,
    "WHIP": 1.059,
    "Kpct": 10.101,
    "BBpct": 2.3569,
    "KBB": 4.29,
    "IP": 22.2,
    "HR9": 0.4,
    "FIP": 2.04,
    "W": 2,
    "L": 1
  },
  {
    "Player": "Touki Toussaint",
    "Season": 2020,
    "ERA": 8.88,
    "WHIP": 1.767,
    "Kpct": 10.101,
    "BBpct": 5.3872,
    "KBB": 1.88,
    "IP": 24.1,
    "HR9": 2.6,
    "FIP": 7.05,
    "W": 0,
    "L": 2
  },
  {
    "Player": "Phillips Valdéz",
    "Season": 2020,
    "ERA": 3.26,
    "WHIP": 1.615,
    "Kpct": 10.101,
    "BBpct": 5.3872,
    "KBB": 1.88,
    "IP": 30.1,
    "HR9": 0.9,
    "FIP": 4.38,
    "W": 1,
    "L": 1
  },
  {
    "Player": "Kyle Wright",
    "Season": 2020,
    "ERA": 5.21,
    "WHIP": 1.553,
    "Kpct": 10.101,
    "BBpct": 8.0808,
    "KBB": 1.25,
    "IP": 38,
    "HR9": 1.7,
    "FIP": 5.9,
    "W": 2,
    "L": 4
  },
  {
    "Player": "Tyler Zuber",
    "Season": 2020,
    "ERA": 4.09,
    "WHIP": 1.591,
    "Kpct": 10.101,
    "BBpct": 6.734,
    "KBB": 1.5,
    "IP": 22,
    "HR9": 1.6,
    "FIP": 5.69,
    "W": 1,
    "L": 2
  },
  {
    "Player": "Adbert Alzolay",
    "Season": 2020,
    "ERA": 2.95,
    "WHIP": 1.172,
    "Kpct": 9.7643,
    "BBpct": 4.3771,
    "KBB": 2.23,
    "IP": 21.1,
    "HR9": 0.4,
    "FIP": 3.05,
    "W": 1,
    "L": 1
  },
  {
    "Player": "Paul Fry",
    "Season": 2020,
    "ERA": 2.45,
    "WHIP": 1.409,
    "Kpct": 9.7643,
    "BBpct": 3.0303,
    "KBB": 3.22,
    "IP": 22,
    "HR9": 1.2,
    "FIP": 3.69,
    "W": 1,
    "L": 0
  },
  {
    "Player": "Brad Hand",
    "Season": 2020,
    "ERA": 2.05,
    "WHIP": 0.773,
    "Kpct": 9.7643,
    "BBpct": 1.3468,
    "KBB": 7.25,
    "IP": 22,
    "HR9": 0,
    "FIP": 1.37,
    "W": 2,
    "L": 1
  },
  {
    "Player": "Merrill Kelly",
    "Season": 2020,
    "ERA": 2.59,
    "WHIP": 0.989,
    "Kpct": 9.7643,
    "BBpct": 1.6835,
    "KBB": 5.8,
    "IP": 31.1,
    "HR9": 1.4,
    "FIP": 3.99,
    "W": 3,
    "L": 2
  },
  {
    "Player": "Chris Mazza",
    "Season": 2020,
    "ERA": 4.8,
    "WHIP": 1.633,
    "Kpct": 9.7643,
    "BBpct": 5.0505,
    "KBB": 1.93,
    "IP": 30,
    "HR9": 0.9,
    "FIP": 4.26,
    "W": 1,
    "L": 2
  },
  {
    "Player": "Félix Peña",
    "Season": 2020,
    "ERA": 4.05,
    "WHIP": 1.313,
    "Kpct": 9.7643,
    "BBpct": 2.6936,
    "KBB": 3.63,
    "IP": 26.2,
    "HR9": 0.7,
    "FIP": 3,
    "W": 3,
    "L": 0
  },
  {
    "Player": "Drew Pomeranz",
    "Season": 2020,
    "ERA": 1.45,
    "WHIP": 1.018,
    "Kpct": 9.7643,
    "BBpct": 3.367,
    "KBB": 2.9,
    "IP": 18.2,
    "HR9": 0.5,
    "FIP": 2.39,
    "W": 1,
    "L": 0
  },
  {
    "Player": "Ryan Pressly",
    "Season": 2020,
    "ERA": 3.43,
    "WHIP": 1.333,
    "Kpct": 9.7643,
    "BBpct": 2.3569,
    "KBB": 4.14,
    "IP": 21,
    "HR9": 0.9,
    "FIP": 2.81,
    "W": 1,
    "L": 3
  },
  {
    "Player": "Gregory Soto",
    "Season": 2020,
    "ERA": 4.3,
    "WHIP": 1.261,
    "Kpct": 9.7643,
    "BBpct": 4.3771,
    "KBB": 2.23,
    "IP": 23,
    "HR9": 0.8,
    "FIP": 3.76,
    "W": 0,
    "L": 1
  },
  {
    "Player": "Erick Fedde",
    "Season": 2020,
    "ERA": 4.29,
    "WHIP": 1.371,
    "Kpct": 9.4276,
    "BBpct": 7.4074,
    "KBB": 1.27,
    "IP": 50.1,
    "HR9": 1.8,
    "FIP": 6.15,
    "W": 2,
    "L": 4
  },
  {
    "Player": "Zack Godley",
    "Season": 2020,
    "ERA": 8.16,
    "WHIP": 1.953,
    "Kpct": 9.4276,
    "BBpct": 4.7138,
    "KBB": 2,
    "IP": 28.2,
    "HR9": 2.8,
    "FIP": 7.1,
    "W": 0,
    "L": 4
  },
  {
    "Player": "Daniel Hudson",
    "Season": 2020,
    "ERA": 6.1,
    "WHIP": 1.258,
    "Kpct": 9.4276,
    "BBpct": 3.7037,
    "KBB": 2.55,
    "IP": 20.2,
    "HR9": 2.6,
    "FIP": 6.29,
    "W": 3,
    "L": 2
  },
  {
    "Player": "Craig Kimbrel",
    "Season": 2020,
    "ERA": 5.28,
    "WHIP": 1.435,
    "Kpct": 9.4276,
    "BBpct": 4.0404,
    "KBB": 2.33,
    "IP": 15.1,
    "HR9": 1.2,
    "FIP": 3.97,
    "W": 0,
    "L": 1
  },
  {
    "Player": "Jorge López",
    "Season": 2020,
    "ERA": 6.69,
    "WHIP": 1.487,
    "Kpct": 9.4276,
    "BBpct": 4.0404,
    "KBB": 2.33,
    "IP": 39,
    "HR9": 1.6,
    "FIP": 5.24,
    "W": 2,
    "L": 2
  },
  {
    "Player": "Daniel Norris",
    "Season": 2020,
    "ERA": 3.25,
    "WHIP": 1.157,
    "Kpct": 9.4276,
    "BBpct": 2.3569,
    "KBB": 4,
    "IP": 27.2,
    "HR9": 0.7,
    "FIP": 2.87,
    "W": 3,
    "L": 1
  }
]
